cryptovwap/__init__.py
cryptovwap/assets/favicon.ico
cryptovwap/assets/style.css
cryptovwap/back/__init__.py
cryptovwap/back/bitvavo.py
cryptovwap/back/exchange.py
cryptovwap/back/helpers.py
cryptovwap/back/kraken.py
cryptovwap/cli.py
cryptovwap/front/__init__.py
cryptovwap/front/head.py
cryptovwap/front/main_page.py
cryptovwap/front/menu.py
cryptovwap-0.1.3.dist-info/entry_points.txt
cryptovwap-0.1.3.dist-info/WHEEL
cryptovwap-0.1.3.dist-info/METADATA
cryptovwap-0.1.3.dist-info/RECORD
