Metadata-Version: 2.1
Name: cryptovwap
Version: 0.1.3
Summary: 
Author: Pablo Manso
Author-email: 92manso@gmail.com
Requires-Python: >=3.10,<4.0
Classifier: Programming Language :: Python :: 3
Classifier: Programming Language :: Python :: 3.10
Requires-Dist: dash (>=2.0.0,<3.0.0)
Requires-Dist: krakenex (>=2.1.0,<3.0.0)
Requires-Dist: pandas (>=1.3.4,<2.0.0)
Requires-Dist: pykrakenapi (>=0.2.3,<0.3.0)
Requires-Dist: python-bitvavo-api (>=1.2.2,<2.0.0)
Requires-Dist: twine (>=3.7.1,<4.0.0)
